[{"id":1,"name":"Andris","city":"Jaipur","email":"afarrance0@google.pl","phone":"512-409-5347","availbty":"YES","bloodgroup":"3XL"},
{"id":2,"name":"Bourke","city":"Ngulahan","email":"bjeffels1@e-recht24.de","phone":"868-523-6989","availbty":"YES","bloodgroup":"L"},
{"id":3,"name":"Sara","city":"Sukhobezvodnoye","email":"spinhorn2@dedecms.com","phone":"698-286-9343","availbty":"NO","bloodgroup":"XS"},
{"id":4,"name":"Breena","city":"Koubia","email":"bsheekey3@etsy.com","phone":"800-706-2614","availbty":"NO","bloodgroup":"S"},
{"id":5,"name":"Ogden","city":"Shiree","email":"oliley4@cbslocal.com","phone":"894-656-5912","availbty":"YES","bloodgroup":"XS"},
{"id":6,"name":"Ulla","city":"Terezín","email":"usmorthit5@reddit.com","phone":"517-849-2093","availbty":"NO","bloodgroup":"YES"},
{"id":7,"name":"Bradan","city":"Tomice","email":"balishoner6@digg.com","phone":"601-564-2633","availbty":"YES","bloodgroup":"S"},
{"id":8,"name":"Morgan","city":"Chinoz","email":"mpearch7@tiny.cc","phone":"179-262-1706","availbty":"YES","bloodgroup":"L"},
{"id":9,"name":"Jordan","city":"Jinqu","email":"jstodd8@mail.ru","phone":"865-155-3268","availbty":"YES","bloodgroup":"XS"},
{"id":10,"name":"Gisele","city":"Pengfang","email":"gcoal9@cloudflare.com","phone":"650-908-0685","availbty":"NO","bloodgroup":"2XL"},
{"id":11,"name":"Bev","city":"Soba","email":"bbambricka@wunderground.com","phone":"972-245-6086","availbty":"NO","bloodgroup":"2XL"},
{"id":12,"name":"Zondra","city":"Jaipur","email":"zbelchampb@go.com","phone":"194-528-4378","availbty":"NO","bloodgroup":"XS"},
{"id":13,"name":"Fiona","city":"Bobigny","email":"fwestcotc@twitpic.com","phone":"762-574-6828","availbty":"NO","bloodgroup":"XS"},
{"id":14,"name":"Pris","city":"Delhi","email":"pcolwelld@unc.edu","phone":"256-253-6871","availbty":"NO","bloodgroup":"2XL"},
{"id":15,"name":"Sybil","city":"Delhi","email":"swinkse@youtu.be","phone":"592-557-2727","availbty":"NO","bloodgroup":"S"},
{"id":16,"name":"Florentia","city":"Sanjiang","email":"fdargief@twitpic.com","phone":"943-558-6157","availbty":"NO","bloodgroup":"XL"},
{"id":17,"name":"Allsun","city":"Delhi","email":"aindruchg@jigsy.com","phone":"430-840-7382","availbty":"NO","bloodgroup":"YES"},
{"id":18,"name":"Fedora","city":"Jaipur","email":"fpinchesh@narod.ru","phone":"207-429-5035","availbty":"NO","bloodgroup":"XL"},
{"id":19,"name":"Beatriz","city":"Saladas","email":"bboldryi@guardian.co.uk","phone":"187-114-5596","availbty":"NO","bloodgroup":"2XL"},
{"id":20,"name":"Georgette","city":"Jaipur","email":"gyockneyj@indiatimes.com","phone":"370-661-6066","availbty":"NO","bloodgroup":"L"},
{"id":21,"name":"Penn","city":"Faraulep","email":"pkubank@abc.net.au","phone":"443-530-2565","availbty":"YES","bloodgroup":"XL"},
{"id":22,"name":"Jephthah","city":"Ngeru","email":"jmarksl@comsenz.com","phone":"545-557-0444","availbty":"YES","bloodgroup":"S"},
{"id":23,"name":"Rees","city":"Rokytnice","email":"rrookem@usatoday.com","phone":"301-163-0877","availbty":"YES","bloodgroup":"YES"},
{"id":24,"name":"Curry","city":"Fatumnasi","email":"ckedwardn@nbcnews.com","phone":"878-759-0124","availbty":"YES","bloodgroup":"S"},
{"id":25,"name":"Silvana","city":"Jaipur","email":"sdudmesho@liveinternet.ru","phone":"214-620-3129","availbty":"NO","bloodgroup":"2XL"},
{"id":26,"name":"Natka","city":"Matriz de Camaragibe","email":"nfullylovep@nasa.gov","phone":"458-394-4224","availbty":"NO","bloodgroup":"YES"},
{"id":27,"name":"Pennie","city":"Delhi","email":"pmaccallumq@upenn.edu","phone":"682-931-1589","availbty":"YES","bloodgroup":"YES"},
{"id":28,"name":"Licha","city":"Delhi","email":"lbellefantr@jalbum.net","phone":"142-692-4784","availbty":"NO","bloodgroup":"L"},
{"id":29,"name":"Corbett","city":"Ejidal","email":"cuttings@t.co","phone":"446-864-6362","availbty":"YES","bloodgroup":"XS"},
{"id":30,"name":"Lianna","city":"Ordynskoye","email":"ljaggerst@friendfeed.com","phone":"487-770-7627","availbty":"NO","bloodgroup":"S"},
{"id":31,"name":"Timothea","city":"L'Aigle","email":"tmacallesteru@amazon.de","phone":"974-403-3220","availbty":"NO","bloodgroup":"2XL"},
{"id":32,"name":"Nessy","city":"Kryry","email":"nmchardyv@freewebs.com","phone":"304-928-1769","availbty":"NO","bloodgroup":"3XL"},
{"id":33,"name":"Kaye","city":"Roissy Charles-de-Gaulle","email":"kadamssonw@cocolog-nifty.com","phone":"307-819-7605","availbty":"NO","bloodgroup":"2XL"},
{"id":34,"name":"Thoma","city":"Shiling","email":"tivanyutinx@reuters.com","phone":"277-116-1623","availbty":"YES","bloodgroup":"XS"},
{"id":35,"name":"Loree","city":"La Virginia","email":"lelcey@cnn.com","phone":"233-843-8953","availbty":"NO","bloodgroup":"YES"},
{"id":36,"name":"Diann","city":"Novotitarovskaya","email":"dbritziusz@sitemeter.com","phone":"958-488-5461","availbty":"NO","bloodgroup":"XL"},
{"id":37,"name":"Ray","city":"Sukadana","email":"rdevillier10@i2i.jp","phone":"288-341-6224","availbty":"YES","bloodgroup":"2XL"},
{"id":38,"name":"Liuka","city":"Yixin","email":"lcoiley11@github.io","phone":"497-311-1824","availbty":"NO","bloodgroup":"3XL"},
{"id":39,"name":"Dillon","city":"Garajati","email":"dtee12@google.nl","phone":"478-162-8922","availbty":"YES","bloodgroup":"YES"},
{"id":40,"name":"Alix","city":"Pueblo Nuevo","email":"awingate13@telegraph.co.uk","phone":"980-780-2124","availbty":"NO","bloodgroup":"XL"},
{"id":41,"name":"Alfy","city":"Paris 17","email":"aabramov14@indiatimes.com","phone":"599-147-7324","availbty":"NO","bloodgroup":"L"},
{"id":42,"name":"Horst","city":"Dearborn","email":"hyurikov15@free.fr","phone":"734-648-9278","availbty":"YES","bloodgroup":"3XL"},
{"id":43,"name":"Evey","city":"Malaga","email":"eleakner16@goodreads.com","phone":"779-943-1312","availbty":"NO","bloodgroup":"S"},
{"id":44,"name":"Hayley","city":"Votuporanga","email":"hginnety17@networkadvertising.org","phone":"846-162-9466","availbty":"NO","bloodgroup":"XL"},
{"id":45,"name":"Raine","city":"Growong Lor","email":"rnice18@noaa.gov","phone":"179-264-2967","availbty":"NO","bloodgroup":"S"},
{"id":46,"name":"Claudell","city":"Independencia","email":"cmates19@1und1.de","phone":"117-864-6961","availbty":"YES","bloodgroup":"YES"},
{"id":47,"name":"Curr","city":"Swiętajno","email":"cchinn1a@godaddy.com","phone":"388-342-9391","availbty":"YES","bloodgroup":"YES"},
{"id":48,"name":"Jonie","city":"Gancheng","email":"jjaneway1b@purevolume.com","phone":"164-591-7437","availbty":"NO","bloodgroup":"2XL"},
{"id":49,"name":"Catina","city":"Kuchurhan","email":"ctrenfield1c@rambler.ru","phone":"372-137-6342","availbty":"NO","bloodgroup":"S"},
{"id":50,"name":"Consuelo","city":"Pakisaji","email":"czambon1d@hubpages.com","phone":"168-574-9938","availbty":"NO","bloodgroup":"XL"},
{"id":51,"name":"Madelyn","city":"Casa Quemada","email":"mmelin1e@istockphoto.com","phone":"242-180-1731","availbty":"NO","bloodgroup":"YES"},
{"id":52,"name":"Nadiya","city":"Dalamdesa Kalapadua","email":"nlawrinson1f@google.fr","phone":"116-916-6432","availbty":"NO","bloodgroup":"2XL"},
{"id":53,"name":"Nickolai","city":"Dosso","email":"nanger1g@twitter.com","phone":"476-328-9427","availbty":"YES","bloodgroup":"XS"},
{"id":54,"name":"Arlette","city":"Yukuhashi","email":"amccourtie1h@wisc.edu","phone":"949-431-0992","availbty":"NO","bloodgroup":"XS"},
{"id":55,"name":"Ailene","city":"Delodpeken","email":"adyka1i@sciencedaily.com","phone":"186-408-2324","availbty":"NO","bloodgroup":"3XL"},
{"id":56,"name":"Perle","city":"Chenfang","email":"pcallaway1j@macromedia.com","phone":"175-548-0707","availbty":"NO","bloodgroup":"YES"},
{"id":57,"name":"Harris","city":"Sukasada","email":"hzanassi1k@spiegel.de","phone":"733-504-3521","availbty":"YES","bloodgroup":"YES"},
{"id":58,"name":"Paten","city":"Cential","email":"pmotto1l@a8.net","phone":"152-937-7717","availbty":"YES","bloodgroup":"S"},
{"id":59,"name":"Dru","city":"Canggou","email":"draddin1m@constantcontact.com","phone":"486-521-2839","availbty":"YES","bloodgroup":"XS"},
{"id":60,"name":"Zaneta","city":"Birmingham","email":"zmcpeice1n@accuweather.com","phone":"205-393-6984","availbty":"NO","bloodgroup":"YES"},
{"id":61,"name":"Vaughn","city":"Duas Igrejas","email":"vbelt1o@ehow.com","phone":"605-782-9796","availbty":"YES","bloodgroup":"YES"},
{"id":62,"name":"Nell","city":"Szlachta","email":"nbraidley1p@yahoo.com","phone":"895-261-9470","availbty":"NO","bloodgroup":"S"},
{"id":63,"name":"Ase","city":"Loznitsa","email":"abrosch1q@shutterfly.com","phone":"443-615-6422","availbty":"YES","bloodgroup":"L"},
{"id":64,"name":"Jerald","city":"São Miguel dos Campos","email":"jmcgrady1r@studiopress.com","phone":"473-336-2677","availbty":"YES","bloodgroup":"XS"},
{"id":65,"name":"Hersh","city":"Jingchuan Chengguanzhen","email":"hdenys1s@51.la","phone":"953-665-3687","availbty":"YES","bloodgroup":"XL"},
{"id":66,"name":"Guglielma","city":"Agkathiá","email":"gwoodhouse1t@utexas.edu","phone":"679-524-1667","availbty":"NO","bloodgroup":"YES"},
{"id":67,"name":"Susann","city":"Kriel","email":"sizzatt1u@stanford.edu","phone":"981-637-3155","availbty":"NO","bloodgroup":"XS"},
{"id":68,"name":"Ethelin","city":"Zhangjiagang","email":"etogher1v@fotki.com","phone":"786-181-4826","availbty":"NO","bloodgroup":"2XL"},
{"id":69,"name":"Dianemarie","city":"Zhigulevsk","email":"dsalamon1w@ovh.net","phone":"280-591-0273","availbty":"NO","bloodgroup":"3XL"},
{"id":70,"name":"Pris","city":"Gajah","email":"pavrahamov1x@bbc.co.uk","phone":"828-469-8453","availbty":"NO","bloodgroup":"L"},
{"id":71,"name":"Lavinie","city":"Pojok","email":"lstive1y@devhub.com","phone":"279-105-1143","availbty":"NO","bloodgroup":"XL"},
{"id":72,"name":"Clara","city":"Xiaomei","email":"cyarrell1z@clickbank.net","phone":"586-501-9942","availbty":"NO","bloodgroup":"L"},
{"id":73,"name":"Livvie","city":"Llusco","email":"lsmethurst20@statcounter.com","phone":"215-613-0220","availbty":"NO","bloodgroup":"XS"},
{"id":74,"name":"Tawsha","city":"Kulykiv","email":"tfoale21@salon.com","phone":"461-346-8185","availbty":"NO","bloodgroup":"S"},
{"id":75,"name":"Ivette","city":"Ust’-Katav","email":"ichambers22@bloglovin.com","phone":"515-145-2745","availbty":"NO","bloodgroup":"2XL"},
{"id":76,"name":"Yardley","city":"Acas","email":"yturl23@123-reg.co.uk","phone":"613-784-6929","availbty":"YES","bloodgroup":"2XL"},
{"id":77,"name":"Caroljean","city":"Chornyanka","email":"cemloch24@cornell.edu","phone":"403-481-7186","availbty":"NO","bloodgroup":"XL"},
{"id":78,"name":"Shaina","city":"Niamey","email":"sbecarra25@bbb.org","phone":"871-790-0949","availbty":"NO","bloodgroup":"XL"},
{"id":79,"name":"Lanette","city":"Longkou","email":"lcolloff26@theguardian.com","phone":"568-141-9944","availbty":"NO","bloodgroup":"XS"},
{"id":80,"name":"Sol","city":"Sandviken","email":"ssharpling27@mtv.com","phone":"716-845-2678","availbty":"YES","bloodgroup":"L"},
{"id":81,"name":"Ernestus","city":"Gurupi","email":"eabramov28@typepad.com","phone":"644-909-2472","availbty":"YES","bloodgroup":"S"},
{"id":82,"name":"Bekki","city":"Langnga","email":"bskowcraft29@delicious.com","phone":"914-148-9983","availbty":"NO","bloodgroup":"2XL"},
{"id":83,"name":"Cyrille","city":"Mata-Utu","email":"ckelf2a@mayoclinic.com","phone":"926-582-5189","availbty":"YES","bloodgroup":"XL"},
{"id":84,"name":"Dewain","city":"Jadowniki","email":"dmcmullen2b@ycombinator.com","phone":"758-676-7085","availbty":"YES","bloodgroup":"XL"},
{"id":85,"name":"Marlane","city":"Hrodna","email":"mbritner2c@naver.com","phone":"598-735-3128","availbty":"NO","bloodgroup":"XL"},
{"id":86,"name":"Taryn","city":"Santa Maria","email":"tharriott2d@163.com","phone":"847-366-8658","availbty":"NO","bloodgroup":"L"},
{"id":87,"name":"Gottfried","city":"Kotadukuh","email":"ggrisewood2e@digg.com","phone":"476-572-9448","availbty":"YES","bloodgroup":"2XL"},
{"id":88,"name":"Welbie","city":"Asamankese","email":"wmacanelley2f@cbsnews.com","phone":"680-835-5075","availbty":"YES","bloodgroup":"L"},
{"id":89,"name":"Marney","city":"San Bautista","email":"misham2g@imageshack.us","phone":"393-731-0872","availbty":"NO","bloodgroup":"3XL"},
{"id":90,"name":"Pietrek","city":"Coromoro","email":"pbraithwait2h@woothemes.com","phone":"544-266-1198","availbty":"YES","bloodgroup":"YES"},
{"id":91,"name":"Malinda","city":"Giồng Riềng","email":"mmacgorman2i@google.es","phone":"594-731-0141","availbty":"NO","bloodgroup":"L"},
{"id":92,"name":"Mahmoud","city":"Évry","email":"mbrame2j@smh.com.au","phone":"999-634-8600","availbty":"YES","bloodgroup":"XS"},
{"id":93,"name":"Angelico","city":"Charlotte","email":"agiggs2k@google.com.hk","phone":"704-365-1105","availbty":"YES","bloodgroup":"2XL"},
{"id":94,"name":"Vidovic","city":"Heiiyugou","email":"vdansey2l@sakura.ne.jp","phone":"243-784-7451","availbty":"YES","bloodgroup":"2XL"},
{"id":95,"name":"Davon","city":"Mineiros","email":"dgoning2m@w3.org","phone":"207-998-9566","availbty":"YES","bloodgroup":"XL"},
{"id":96,"name":"Ingaborg","city":"Hankha","email":"ilinturn2n@omniture.com","phone":"932-245-3648","availbty":"NO","bloodgroup":"L"},
{"id":97,"name":"Mellisa","city":"Ḩāfiz̧ Moghul","email":"mwestraw2o@tumblr.com","phone":"868-370-8179","availbty":"NO","bloodgroup":"2XL"},
{"id":98,"name":"Smitty","city":"Sathon","email":"sraubenheimer2p@state.gov","phone":"439-880-0717","availbty":"YES","bloodgroup":"L"},
{"id":99,"name":"Kale","city":"Novallas","email":"kcorrie2q@hatena.ne.jp","phone":"340-155-8590","availbty":"YES","bloodgroup":"S"},
{"id":100,"name":"Penelopa","city":"Mirandopólis","email":"pmadeley2r@netlog.com","phone":"541-555-3917","availbty":"NO","bloodgroup":"YES"},
{"id":101,"name":"Raimondo","city":"Nanyuan","email":"rmollnar2s@rambler.ru","phone":"747-758-1954","availbty":"YES","bloodgroup":"XS"},
{"id":102,"name":"Letizia","city":"Brokopondo","email":"lhuckfield2t@wix.com","phone":"144-243-1987","availbty":"NO","bloodgroup":"YES"},
{"id":103,"name":"Kassi","city":"Hesperange","email":"kkloska2u@phpbb.com","phone":"320-833-6346","availbty":"NO","bloodgroup":"L"},
{"id":104,"name":"Yuma","city":"Yaogou","email":"ybattelle2v@huffingtonpost.com","phone":"792-651-3881","availbty":"YES","bloodgroup":"2XL"},
{"id":105,"name":"Averill","city":"Padangtiji","email":"atregear2w@google.es","phone":"649-233-3783","availbty":"YES","bloodgroup":"S"},
{"id":106,"name":"Madeleine","city":"Nueva Ocotepeque","email":"mtowers2x@cdc.gov","phone":"205-499-1320","availbty":"NO","bloodgroup":"S"},
{"id":107,"name":"Jaquenetta","city":"Kannus","email":"jshillinglaw2y@un.org","phone":"560-814-4796","availbty":"NO","bloodgroup":"YES"},
{"id":108,"name":"Kyle","city":"Mantes-la-Jolie","email":"ksoff2z@360.cn","phone":"703-424-6797","availbty":"YES","bloodgroup":"YES"},
{"id":109,"name":"Chelsea","city":"Eisen","email":"cwaggatt30@cdbaby.com","phone":"450-436-7710","availbty":"NO","bloodgroup":"3XL"},
{"id":110,"name":"Randall","city":"L-Iklin","email":"radrianello31@about.me","phone":"264-174-5543","availbty":"YES","bloodgroup":"2XL"},
{"id":111,"name":"Gustaf","city":"Quinchía","email":"grighy32@arizona.edu","phone":"797-176-6452","availbty":"YES","bloodgroup":"XL"},
{"id":112,"name":"Crosby","city":"Moluo","email":"cdugan33@netscape.com","phone":"785-235-6213","availbty":"YES","bloodgroup":"XL"},
{"id":113,"name":"Beverly","city":"Manhush","email":"bsigne34@uiuc.edu","phone":"799-278-5317","availbty":"NO","bloodgroup":"2XL"},
{"id":114,"name":"Sunshine","city":"Vágia","email":"sallender35@wikispaces.com","phone":"135-401-8636","availbty":"NO","bloodgroup":"2XL"},
{"id":115,"name":"Fields","city":"Al Jabīn","email":"fgenner36@hugedomains.com","phone":"523-535-4694","availbty":"YES","bloodgroup":"S"},
{"id":116,"name":"Brear","city":"Oklahoma City","email":"bescale37@1688.com","phone":"405-271-7163","availbty":"NO","bloodgroup":"YES"},
{"id":117,"name":"Dalila","city":"Badar","email":"dwennington38@rediff.com","phone":"854-636-8172","availbty":"NO","bloodgroup":"XS"},
{"id":118,"name":"Julieta","city":"Lampihung","email":"jive39@samsung.com","phone":"155-630-9363","availbty":"NO","bloodgroup":"3XL"},
{"id":119,"name":"Brooks","city":"Pittsburgh","email":"bkinman3a@bloglines.com","phone":"-228-6386","availbty":"YES","bloodgroup":"YES"},
{"id":120,"name":"Trista","city":"Banjar Dukuh","email":"togan3b@ezinearticles.com","phone":"492-797-8957","availbty":"NO","bloodgroup":"YES"},
{"id":121,"name":"Pru","city":"Longjin","email":"pfullagar3c@nps.gov","phone":"201-267-3968","availbty":"NO","bloodgroup":"2XL"},
{"id":122,"name":"Simeon","city":"Jingtailu","email":"sbritney3d@yellowpages.com","phone":"146-670-7680","availbty":"YES","bloodgroup":"L"},
{"id":123,"name":"Cortney","city":"Berezovo","email":"cbartozzi3e@msn.com","phone":"198-479-2375","availbty":"NO","bloodgroup":"XS"},
{"id":124,"name":"Rosalinde","city":"Porto Seguro","email":"rtebbutt3f@craigslist.org","phone":"885-535-4593","availbty":"NO","bloodgroup":"XL"},
{"id":125,"name":"Tine","city":"Riangkroko","email":"tcrimpe3g@posterous.com","phone":"701-337-2377","availbty":"NO","bloodgroup":"L"},
{"id":126,"name":"Jobye","city":"Kaišiadorys","email":"jroughley3h@dot.gov","phone":"196-629-5429","availbty":"NO","bloodgroup":"YES"},
{"id":127,"name":"Lynette","city":"Xiaomiaozi","email":"lcarff3i@google.de","phone":"353-875-6227","availbty":"NO","bloodgroup":"L"},
{"id":128,"name":"Jessalin","city":"Talipan","email":"jchoupin3j@google.ca","phone":"907-378-0031","availbty":"NO","bloodgroup":"L"},
{"id":129,"name":"Walther","city":"Taishang","email":"wsima3k@gnu.org","phone":"808-360-5709","availbty":"YES","bloodgroup":"2XL"},
{"id":130,"name":"Hester","city":"Galitsy","email":"hlente3l@java.com","phone":"939-857-9267","availbty":"NO","bloodgroup":"XL"},
{"id":131,"name":"Desi","city":"Xiaojinkou","email":"dcorwin3m@topsy.com","phone":"472-102-8898","availbty":"YES","bloodgroup":"L"},
{"id":132,"name":"Brianne","city":"Dongping","email":"bconneau3n@nsw.gov.au","phone":"681-960-0946","availbty":"NO","bloodgroup":"L"},
{"id":133,"name":"Lucais","city":"Pawitan","email":"lginn3o@issuu.com","phone":"396-286-5651","availbty":"YES","bloodgroup":"L"},
{"id":134,"name":"Mirabel","city":"Ripky","email":"mollet3p@bigcartel.com","phone":"902-638-2640","availbty":"NO","bloodgroup":"3XL"},
{"id":135,"name":"Ailbert","city":"Bachuan","email":"amcnee3q@skyrock.com","phone":"139-283-5830","availbty":"YES","bloodgroup":"3XL"},
{"id":136,"name":"Ethelda","city":"Mixco","email":"epetkov3r@yahoo.co.jp","phone":"976-473-5758","availbty":"NO","bloodgroup":"S"},
{"id":137,"name":"Pancho","city":"Balboa","email":"pblandford3s@foxnews.com","phone":"424-760-2838","availbty":"YES","bloodgroup":"2XL"},
{"id":138,"name":"Knox","city":"Mertert","email":"kfalkner3t@samsung.com","phone":"636-302-4978","availbty":"YES","bloodgroup":"S"},
{"id":139,"name":"Melisa","city":"Kranggan","email":"msleet3u@kickstarter.com","phone":"657-719-7103","availbty":"NO","bloodgroup":"XL"},
{"id":140,"name":"Chaim","city":"Vođinci","email":"ccorington3v@ustream.tv","phone":"555-488-1978","availbty":"YES","bloodgroup":"XL"},
{"id":141,"name":"Lucian","city":"Gaopi","email":"lspeariett3w@wikipedia.org","phone":"256-297-2149","availbty":"YES","bloodgroup":"S"},
{"id":142,"name":"Leon","city":"Ponta Delgada","email":"lriepl3x@alexa.com","phone":"847-552-5538","availbty":"YES","bloodgroup":"L"},
{"id":143,"name":"Jarrett","city":"Lobatse","email":"jrawlcliffe3y@businessinsider.com","phone":"372-288-5287","availbty":"YES","bloodgroup":"YES"},
{"id":144,"name":"Nikolai","city":"Buga","email":"nhowgego3z@istockphoto.com","phone":"904-498-8681","availbty":"YES","bloodgroup":"3XL"},
{"id":145,"name":"Isadora","city":"Beiping","email":"isherebrooke40@i2i.jp","phone":"108-974-3662","availbty":"NO","bloodgroup":"S"},
{"id":146,"name":"Cynthie","city":"Amizmiz","email":"cnovotni41@alibaba.com","phone":"465-166-4708","availbty":"NO","bloodgroup":"S"},
{"id":147,"name":"Mallory","city":"Broto","email":"mbutten42@ftc.gov","phone":"549-888-7876","availbty":"YES","bloodgroup":"S"},
{"id":148,"name":"Kania","city":"Villanueva","email":"ksage43@spiegel.de","phone":"604-862-8701","availbty":"NO","bloodgroup":"S"},
{"id":149,"name":"Kimbra","city":"Ārt Khwājah","email":"kmarch44@patch.com","phone":"569-687-2752","availbty":"NO","bloodgroup":"XL"},
{"id":150,"name":"Harvey","city":"El Peñol","email":"hjenman45@narod.ru","phone":"377-200-5544","availbty":"YES","bloodgroup":"L"},
{"id":151,"name":"Pauly","city":"Karlovo","email":"pmelburg46@webeden.co.uk","phone":"315-202-9896","availbty":"NO","bloodgroup":"2XL"},
{"id":152,"name":"Carolynn","city":"Baratan","email":"ccortnay47@nyu.edu","phone":"110-352-1808","availbty":"NO","bloodgroup":"2XL"},
{"id":153,"name":"Kaitlyn","city":"Lumphăt","email":"kdickin48@chronoengine.com","phone":"216-978-5836","availbty":"NO","bloodgroup":"YES"},
{"id":154,"name":"Elwyn","city":"Xuezhen","email":"eclubb49@wp.com","phone":"103-317-4669","availbty":"YES","bloodgroup":"S"},
{"id":155,"name":"Krystle","city":"Göteborg","email":"kpratt4a@technorati.com","phone":"214-173-2316","availbty":"NO","bloodgroup":"2XL"},
{"id":156,"name":"Elset","city":"Chongwen","email":"ecobbled4b@artisteer.com","phone":"145-273-4197","availbty":"NO","bloodgroup":"3XL"},
{"id":157,"name":"Melicent","city":"Sukoanyar","email":"mewells4c@macromedia.com","phone":"581-179-9830","availbty":"NO","bloodgroup":"XS"},
{"id":158,"name":"Dana","city":"Torbeck","email":"despinay4d@youku.com","phone":"465-151-2558","availbty":"NO","bloodgroup":"3XL"},
{"id":159,"name":"Demetra","city":"Stírion","email":"darton4e@upenn.edu","phone":"238-857-9604","availbty":"NO","bloodgroup":"2XL"},
{"id":160,"name":"Arlie","city":"Jielong","email":"abrodeau4f@hp.com","phone":"826-148-6607","availbty":"NO","bloodgroup":"2XL"},
{"id":161,"name":"Cyrillus","city":"San Lucas Tolimán","email":"cdilgarno4g@symantec.com","phone":"813-891-2521","availbty":"YES","bloodgroup":"S"},
{"id":162,"name":"Timmy","city":"Richmond","email":"tcourcey4h@ftc.gov","phone":"793-815-9474","availbty":"YES","bloodgroup":"YES"},
{"id":163,"name":"Gwenette","city":"Pledo","email":"gtully4i@mac.com","phone":"460-622-5073","availbty":"NO","bloodgroup":"L"},
{"id":164,"name":"Lou","city":"Domašinec","email":"lbrady4j@lycos.com","phone":"517-635-1763","availbty":"YES","bloodgroup":"S"},
{"id":165,"name":"Leanna","city":"Rominimbang","email":"lraynes4k@hexun.com","phone":"913-852-9736","availbty":"NO","bloodgroup":"YES"},
{"id":166,"name":"Byron","city":"Shanghang","email":"bkingsnoad4l@com.com","phone":"547-649-9191","availbty":"YES","bloodgroup":"L"},
{"id":167,"name":"Benjy","city":"Al Jabīn","email":"bgenicke4m@seesaa.net","phone":"714-469-1008","availbty":"YES","bloodgroup":"S"},
{"id":168,"name":"Brockie","city":"Khalkhāl","email":"breal4n@shop-pro.jp","phone":"438-859-5391","availbty":"YES","bloodgroup":"3XL"},
{"id":169,"name":"Kirk","city":"Dagsar","email":"klamont4o@pagesperso-orange.fr","phone":"899-141-4446","availbty":"YES","bloodgroup":"XS"},
{"id":170,"name":"Ric","city":"Shuangfeng","email":"rhigbin4p@dot.gov","phone":"194-706-0700","availbty":"YES","bloodgroup":"XL"},
{"id":171,"name":"Tarrah","city":"Magoúla","email":"tenticott4q@opera.com","phone":"246-775-5027","availbty":"NO","bloodgroup":"XS"},
{"id":172,"name":"Arnie","city":"Halat","email":"ajanuszewicz4r@boston.com","phone":"933-298-8877","availbty":"YES","bloodgroup":"XL"},
{"id":173,"name":"Feliza","city":"Semiring","email":"fdemeis4s@icq.com","phone":"727-315-9473","availbty":"NO","bloodgroup":"S"},
{"id":174,"name":"Hamish","city":"Tambakmerak","email":"hhuxham4t@1und1.de","phone":"799-489-4049","availbty":"YES","bloodgroup":"YES"},
{"id":175,"name":"Mirelle","city":"Mombok","email":"msisse4u@tripadvisor.com","phone":"415-435-9270","availbty":"NO","bloodgroup":"XL"},
{"id":176,"name":"Shandeigh","city":"Campo","email":"sandrys4v@jugem.jp","phone":"881-237-6057","availbty":"NO","bloodgroup":"L"},
{"id":177,"name":"Miriam","city":"Hikone","email":"mpadgham4w@reddit.com","phone":"803-414-7126","availbty":"NO","bloodgroup":"S"},
{"id":178,"name":"Denney","city":"Tvøroyri","email":"ddampier4x@ning.com","phone":"975-423-1524","availbty":"YES","bloodgroup":"XL"},
{"id":179,"name":"Bram","city":"Bassano","email":"bmanuely4y@google.es","phone":"608-909-1682","availbty":"YES","bloodgroup":"S"},
{"id":180,"name":"Gothart","city":"Mandaluyong City","email":"groalfe4z@hc360.com","phone":"465-654-3208","availbty":"YES","bloodgroup":"YES"},
{"id":181,"name":"Arvie","city":"Al Bāţinah","email":"atait50@barnesandnoble.com","phone":"602-835-8381","availbty":"YES","bloodgroup":"3XL"},
{"id":182,"name":"Galven","city":"Duba","email":"gdawton51@tuttocitta.it","phone":"495-749-5879","availbty":"YES","bloodgroup":"L"},
{"id":183,"name":"Jerrie","city":"Banarankrajan","email":"jallcock52@github.io","phone":"375-550-8229","availbty":"YES","bloodgroup":"3XL"},
{"id":184,"name":"Ondrea","city":"Lagayan","email":"ocargo53@omniture.com","phone":"982-824-5194","availbty":"NO","bloodgroup":"2XL"},
{"id":185,"name":"Clare","city":"Fonte da Vaca","email":"cpendlebery54@rediff.com","phone":"750-594-4201","availbty":"NO","bloodgroup":"S"},
{"id":186,"name":"Davida","city":"Orsk","email":"dbarfield55@businessweek.com","phone":"243-593-4999","availbty":"NO","bloodgroup":"L"},
{"id":187,"name":"Jocelin","city":"Jönköping","email":"jdagostino56@wunderground.com","phone":"306-318-1922","availbty":"NO","bloodgroup":"L"},
{"id":188,"name":"Henryetta","city":"San Isidro","email":"hstoving57@opensource.org","phone":"809-534-2122","availbty":"NO","bloodgroup":"YES"},
{"id":189,"name":"Chancey","city":"Margarita","email":"charrow58@privacy.gov.au","phone":"405-350-3020","availbty":"YES","bloodgroup":"XL"},
{"id":190,"name":"Kippie","city":"Sibulan","email":"kdegregario59@weather.com","phone":"760-967-8221","availbty":"YES","bloodgroup":"XL"},
{"id":191,"name":"Leontine","city":"Liuhu","email":"lmeiningen5a@mediafire.com","phone":"883-847-2088","availbty":"NO","bloodgroup":"YES"},
{"id":192,"name":"Adeline","city":"Vancouver","email":"agrannell5b@flickr.com","phone":"360-460-6274","availbty":"NO","bloodgroup":"S"},
{"id":193,"name":"Doro","city":"Chakaray","email":"dbutt5c@angelfire.com","phone":"901-790-5061","availbty":"NO","bloodgroup":"S"},
{"id":194,"name":"Theodore","city":"Göteborg","email":"troake5d@infoseek.co.jp","phone":"763-902-9093","availbty":"YES","bloodgroup":"XL"},
{"id":195,"name":"Derrek","city":"Tilburg","email":"dkrinks5e@hud.gov","phone":"920-803-5724","availbty":"YES","bloodgroup":"L"},
{"id":196,"name":"Rachele","city":"Damiao","email":"rgaul5f@cisco.com","phone":"350-233-5127","availbty":"NO","bloodgroup":"XL"},
{"id":197,"name":"Tremayne","city":"Khadīr","email":"tblanch5g@de.vu","phone":"461-199-6653","availbty":"YES","bloodgroup":"XL"},
{"id":198,"name":"Fonsie","city":"Zhangyelu","email":"fdemetz5h@seattletimes.com","phone":"283-353-9009","availbty":"YES","bloodgroup":"3XL"},
{"id":199,"name":"Anneliese","city":"Levski","email":"ariseley5i@dion.ne.jp","phone":"320-181-1049","availbty":"NO","bloodgroup":"S"},
{"id":200,"name":"Jillene","city":"Samho-rodongjagu","email":"jhurdle5j@scribd.com","phone":"450-117-8084","availbty":"NO","bloodgroup":"3XL"}]